Workbook

Sheet Model Assumptions
A1: Model Assumptions | D1: currency in euros | G1: 1 | H1: Best case
G2: 2 | H2: Base case
A3: Selected case | B3: 2 | G3: 3 | H3: Worst case
A5: Inflation
A6: Expected long term inflation India | B6: 0.05
A7: Expected long term inflation Vietnam | B7: 0.06 | F7: Vietnam is a faster-growing emerging market → slightly higher inflation
A10: PRICE OF PRODUCTION
A11: Price of production in India | B11: 12000
A12: Price of production in Vietnam | B12: 9500 | F12: Lower labor + cost in Vietnam → cheaper production
A14: Estimated initial investment
A15: Best case | B15: 270000000
A16: Base case | B16: 300000000
A17: Worst case | B17: 340000000
A19: Useful life of years | B19: 10
A21: Working Capital
A22: DSO | B22: 35
A23: DIO (Inventory days) | B23: 35
A24: DPO (Payable days) | B24: 25
A25: net wc cycle | B25: =B22+B23-B24 -> 45
A27: FINANCING FACILITIES
A29: Senior Debt (Loan)
A31: Loan amount | B31: 200000000
A32: Interest rate | B32: 0.09
A33: Tenure | B33: 10
A36: Loan schedule | C36: 0 | D36: 1 | E36: 2 | F36: 3 | G36: 4 | H36: 5 | I36: 6 | J36: 7 | K36: 8 | L36: 9 | M36: 10
A37: Repayement % | C37: 0 | D37: 0 | E37: 0.05 | F37: 0.05 | G37: 0.1 | H37: 0.1 | I37: 0.15 | J37: 0.15 | K37: 0.15 | L37: 0.15 | M37: 0.1
A40: Covenants
A42: Minimum production/sales:
A43: 👉 Must sell at least 1,00,000 units per year
A45: If not:
A46: 👉 Penalty = €1,000,000 per year
A49: Tax rate | B49: 0.25
A51: Residual value of the project | B51: 50000000

Sheet Saving Forecast 
A1: Saving Forecast
A3: Best case | B3: 240000
A4: Base case | B4: 200000
A5: Worst case | B5: 160000
A7: Volume in units | C7: 1 | D7: 2 | E7: 3 | F7: 4 | G7: 5 | H7: 6 | I7: 7 | J7: 8 | K7: 9 | L7: 10
A8: Best case | C8: =$B$3*C15 -> 60000 | D8: =$B$3*D15 -> 72000 | E8: =$B$3*E15 -> 132000 | F8: =$B$3*F15 -> 180000 | G8: =$B$3*G15 -> 216000 | H8: =$B$3*H15 -> 228000 | I8: =$B$3*I15 -> 240000 | J8: =$B$3*J15 -> 240000 | ... L8: =$B$3*L15 -> 240000
A9: Base case | C9: =$B$4*C16 -> 20000 | D9: =$B$4*D16 -> 40000 | E9: =$B$4*E16 -> 80000 | F9: =$B$4*F16 -> 120000 | G9: =$B$4*G16 -> 150000 | H9: =$B$4*H16 -> 170000 | I9: =$B$4*I16 -> 180000 | J9: =$B$4*J16 -> 190000 | ... L9: =$B$4*L16 -> 190000
A10: Worst case | C10: =$B$5*C17 -> 8000 | D10: =$B$5*D17 -> 16000 | E10: =$B$5*E17 -> 40000 | F10: =$B$5*F17 -> 64000 | G10: =$B$5*G17 -> 88000 | H10: =$B$5*H17 -> 104000 | I10: =$B$5*I17 -> 112000 | J10: =$B$5*J17 -> 120000 | ... L10: =$B$5*L17 -> 136000
A11: Selected case | C11: =CHOOSE('Model Assumptions'!$B$3,'Saving Forecast '!C8,'Saving Forecast '!C9,'Saving Forecast '!C10) -> 20000 | D11: =CHOOSE('Model Assumptions'!$B$3,'Saving Forecast '!D8,'Saving Forecast '!D9,'Saving Forecast '!D10) -> 40000 | E11: =CHOOSE('Model Assumptions'!$B$3,'Saving Forecast '!E8,'Saving Forecast '!E9,'Saving Forecast '!E10) -> 80000 | F11: =CHOOSE('Model Assumptions'!$B$3,'Saving Forecast '!F8,'Saving Forecast '!F9,'Saving Forecast '!F10) -> 120000 | G11: =CHOOSE('Model Assumptions'!$B$3,'Saving Forecast '!G8,'Saving Forecast '!G9,'Saving Forecast '!G10) -> 150000 | H11: =CHOOSE('Model Assumptions'!$B$3,'Saving Forecast '!H8,'Saving Forecast '!H9,'Saving Forecast '!H10) -> 170000 | I11: =CHOOSE('Model Assumptions'!$B$3,'Saving Forecast '!I8,'Saving Forecast '!I9,'Saving Forecast '!I10) -> 180000 | J11: =CHOOSE('Model Assumptions'!$B$3,'Saving Forecast '!J8,'Saving Forecast '!J9,'Saving Forecast '!J10) -> 190000 | ... L11: =CHOOSE('Model Assumptions'!$B$3,'Saving Forecast '!L8,'Saving Forecast '!L9,'Saving Forecast '!L10) -> 190000
A14: Productivity as % | C14: 1 | D14: 2 | E14: 3 | F14: 4 | G14: 5 | H14: 6 | I14: 7 | J14: 8 | K14: 9 | L14: 10
A15: Best case | C15: 0.25 | D15: 0.3 | E15: 0.55 | F15: 0.75 | G15: 0.9 | H15: 0.95 | I15: 1 | J15: 1 | K15: 1 | L15: 1
A16: Base case | C16: 0.1 | D16: 0.2 | E16: 0.4 | F16: 0.6 | G16: 0.75 | H16: 0.85 | I16: 0.9 | J16: 0.95 | K16: 0.95 | L16: 0.95
A17: Worst case | C17: 0.05 | D17: 0.1 | E17: 0.25 | F17: 0.4 | G17: 0.55 | H17: 0.65 | I17: 0.7 | J17: 0.75 | K17: 0.8 | L17: 0.85
A20: Expected long term inflation in India | B20: ='Model Assumptions'!B6 -> 0.05
A21: Expected long term inflation in Vietnam | B21: ='Model Assumptions'!B7 -> 0.06
A24: PRICE OF PRODUCTION(EUR)
A25: Price of production in India | C25: ='Model Assumptions'!B11 -> 12000 | D25: =C25*(1+$B$20) -> 12600 | E25: =D25*(1+$B$20) -> 13230 | F25: =E25*(1+$B$20) -> 13891.5 | G25: =F25*(1+$B$20) -> 14586.075 | H25: =G25*(1+$B$20) -> 15315.379 | I25: =H25*(1+$B$20) -> 16081.148 | J25: =I25*(1+$B$20) -> 16885.205 | K25: =J25*(1+$B$20) -> 17729.465 | L25: =K25*(1+$B$20) -> 18615.939
A26: Price of production in Vietnam | C26: ='Model Assumptions'!B12 -> 9500 | D26: =C26*(1+$B$21) -> 10070 | E26: =D26*(1+$B$21) -> 10674.2 | F26: =E26*(1+$B$21) -> 11314.652 | G26: =F26*(1+$B$21) -> 11993.531 | H26: =G26*(1+$B$21) -> 12713.143 | I26: =H26*(1+$B$21) -> 13475.932 | J26: =I26*(1+$B$21) -> 14284.487 | K26: =J26*(1+$B$21) -> 15141.557 | L26: =K26*(1+$B$21) -> 16050.05
A27: Saving per unit | C27: =C25-C26 -> 2500 | D27: =D25-D26 -> 2530 | E27: =E25-E26 -> 2555.8 | F27: =F25-F26 -> 2576.848 | G27: =G25-G26 -> 2592.5439 | H27: =H25-H26 -> 2602.2358 | I27: =I25-I26 -> 2605.2161 | J27: =J25-J26 -> 2600.7176 | ... L27: =L25-L26 -> 2565.8885
A30: Total savings | C30: 1 | D30: 2 | E30: 3 | F30: 4 | G30: 5 | H30: 6 | I30: 7 | J30: 8 | K30: 9 | L30: 10
A31: Best case | C31: =C8*C$27 -> 150000000 | D31: =D8*D$27 -> 182160000 | E31: =E$27*E8 -> 3.373656e+08 | F31: =F8*F$27 -> 4.6383264e+08 | G31: =G$27*G8 -> 5.5998948e+08 | H31: =H8*H$27 -> 5.9330975e+08 | I31: =I$27*I8 -> 6.2525187e+08 | J31: =J8*J$27 -> 6.2417223e+08 | K31: =K$27*K8 -> 6.2109807e+08 | L31: =L$27*L8 -> 6.1581324e+08
A32: Base case | C32: =C9*C$27 -> 50000000 | D32: =D9*D$27 -> 101200000 | E32: =E$27*E9 -> 2.04464e+08 | F32: =F9*F$27 -> 3.0922176e+08 | G32: =G$27*G9 -> 3.8888158e+08 | H32: =H9*H$27 -> 4.4238008e+08 | I32: =I$27*I9 -> 4.689389e+08 | J32: =J9*J$27 -> 4.9413635e+08 | K32: =K$27*K9 -> 4.9170264e+08 | L32: =L$27*L9 -> 4.8751881e+08
A33: Worst case | C33: =C10*C$27 -> 20000000 | D33: =D10*D$27 -> 40480000 | E33: =E$27*E10 -> 1.02232e+08 | F33: =F10*F$27 -> 1.6491827e+08 | G33: =G$27*G10 -> 2.2814386e+08 | H33: =H10*H$27 -> 2.7063252e+08 | I33: =I$27*I10 -> 2.9178421e+08 | J33: =J10*J$27 -> 3.1208611e+08 | K33: =K$27*K10 -> 3.312523e+08 | L33: =L$27*L10 -> 3.4896083e+08
A34: Selected case | C34: =CHOOSE('Model Assumptions'!$B$3,'Saving Forecast '!C31,'Saving Forecast '!C32,'Saving Forecast '!C33) -> 50000000 | D34: =CHOOSE('Model Assumptions'!$B$3,'Saving Forecast '!D31,'Saving Forecast '!D32,'Saving Forecast '!D33) -> 101200000 | E34: =CHOOSE('Model Assumptions'!$B$3,'Saving Forecast '!E31,'Saving Forecast '!E32,'Saving Forecast '!E33) -> 2.04464e+08 | F34: =CHOOSE('Model Assumptions'!$B$3,'Saving Forecast '!F31,'Saving Forecast '!F32,'Saving Forecast '!F33) -> 3.0922176e+08 | G34: =CHOOSE('Model Assumptions'!$B$3,'Saving Forecast '!G31,'Saving Forecast '!G32,'Saving Forecast '!G33) -> 3.8888158e+08 | H34: =CHOOSE('Model Assumptions'!$B$3,'Saving Forecast '!H31,'Saving Forecast '!H32,'Saving Forecast '!H33) -> 4.4238008e+08 | I34: =CHOOSE('Model Assumptions'!$B$3,'Saving Forecast '!I31,'Saving Forecast '!I32,'Saving Forecast '!I33) -> 4.689389e+08 | J34: =CHOOSE('Model Assumptions'!$B$3,'Saving Forecast '!J31,'Saving Forecast '!J32,'Saving Forecast '!J33) -> 4.9413635e+08 | ... L34: =CHOOSE('Model Assumptions'!$B$3,'Saving Forecast '!L31,'Saving Forecast '!L32,'Saving Forecast '!L33) -> 4.8751881e+08

Sheet Fixed Asset Roll-Forward
A1: Fixed Asset Roll-Forward
A3: Estimated initial investment
A4: Best case | B4: ='Model Assumptions'!B15 -> 270000000
A5: Base case | B5: ='Model Assumptions'!B16 -> 300000000
A6: Worst case | B6: ='Model Assumptions'!B17 -> 340000000
A8: useful life | B8: 10
A10: Investment plan | C10: 0 | D10: 1 | E10: 2 | F10: 3 | G10: 4 | H10: 5 | I10: 6 | J10: 7 | K10: 8 | L10: 9 | M10: 10
C11: 0.8 | D11: 0.1 | E11: 0.1 | F11: 0.03 | G11: 0.03 | H11: 0.03 | I11: 0.03 | J11: 0.03 | K11: 0.03 | L11: 0.03 | M11: 0.03
A13: beginning pp&e | D13: =CHOOSE('Model Assumptions'!$B$3,'Fixed Asset Roll-Forward'!$B4,'Fixed Asset Roll-Forward'!$B5,'Fixed Asset Roll-Forward'!$B6)*'Fixed Asset Roll-Forward'!C11 -> 240000000 | E13: =D16 -> 246000000 | F13: =E16 -> 249000000 | G13: =F16 -> 228000000 | H13: =G16 -> 206100000 | I13: =H16 -> 183300000 | J13: =I16 -> 159600000 | K13: =J16 -> 135000000 | L13: =K16 -> 109500000 | M13: =L16 -> 83100000
A14: capex | D14: =CHOOSE('Model Assumptions'!$B$3,'Fixed Asset Roll-Forward'!$B4,'Fixed Asset Roll-Forward'!$B5,'Fixed Asset Roll-Forward'!$B6)*'Fixed Asset Roll-Forward'!D11 -> 30000000 | E14: =CHOOSE('Model Assumptions'!$B$3,'Fixed Asset Roll-Forward'!$B4,'Fixed Asset Roll-Forward'!$B5,'Fixed Asset Roll-Forward'!$B6)*'Fixed Asset Roll-Forward'!E11 -> 30000000 | F14: =CHOOSE('Model Assumptions'!$B$3,'Fixed Asset Roll-Forward'!$B4,'Fixed Asset Roll-Forward'!$B5,'Fixed Asset Roll-Forward'!$B6)*'Fixed Asset Roll-Forward'!F11 -> 9000000 | G14: =CHOOSE('Model Assumptions'!$B$3,'Fixed Asset Roll-Forward'!$B4,'Fixed Asset Roll-Forward'!$B5,'Fixed Asset Roll-Forward'!$B6)*'Fixed Asset Roll-Forward'!G11 -> 9000000 | H14: =CHOOSE('Model Assumptions'!$B$3,'Fixed Asset Roll-Forward'!$B4,'Fixed Asset Roll-Forward'!$B5,'Fixed Asset Roll-Forward'!$B6)*'Fixed Asset Roll-Forward'!H11 -> 9000000 | I14: =CHOOSE('Model Assumptions'!$B$3,'Fixed Asset Roll-Forward'!$B4,'Fixed Asset Roll-Forward'!$B5,'Fixed Asset Roll-Forward'!$B6)*'Fixed Asset Roll-Forward'!I11 -> 9000000 | J14: =CHOOSE('Model Assumptions'!$B$3,'Fixed Asset Roll-Forward'!$B4,'Fixed Asset Roll-Forward'!$B5,'Fixed Asset Roll-Forward'!$B6)*'Fixed Asset Roll-Forward'!J11 -> 9000000 | K14: =CHOOSE('Model Assumptions'!$B$3,'Fixed Asset Roll-Forward'!$B4,'Fixed Asset Roll-Forward'!$B5,'Fixed Asset Roll-Forward'!$B6)*'Fixed Asset Roll-Forward'!K11 -> 9000000 | ... M14: =CHOOSE('Model Assumptions'!$B$3,'Fixed Asset Roll-Forward'!$B4,'Fixed Asset Roll-Forward'!$B5,'Fixed Asset Roll-Forward'!$B6)*'Fixed Asset Roll-Forward'!M11 -> 9000000
A15: D&A | D15: =D29 -> -24000000 | E15: =E29 -> -27000000 | F15: =F29 -> -30000000 | G15: =G29 -> -30900000 | H15: =H29 -> -31800000 | I15: =I29 -> -32700000 | J15: =J29 -> -33600000 | K15: =K29 -> -34500000 | ... M15: =M29 -> -36300000
A16: Ending pp&e | D16: =SUM(D13:D15) -> 246000000 | E16: =SUM(E13:E15) -> 249000000 | F16: =SUM(F13:F15) -> 228000000 | G16: =SUM(G13:G15) -> 206100000 | H16: =SUM(H13:H15) -> 183300000 | I16: =SUM(I13:I15) -> 159600000 | J16: =SUM(J13:J15) -> 135000000 | K16: =SUM(K13:K15) -> 109500000 | ... M16: =SUM(M13:M15) -> 55800000
A18: D&A SCHEDULE
A19: dep year 1 | D19: =-$D$13/10 -> -24000000 | E19: =-$D$13/10 -> -24000000 | F19: =-$D$13/10 -> -24000000 | G19: =-$D$13/10 -> -24000000 | H19: =-$D$13/10 -> -24000000 | I19: =-$D$13/10 -> -24000000 | J19: =-$D$13/10 -> -24000000 | K19: =-$D$13/10 -> -24000000 | ... M19: =-$D$13/10 -> -24000000
A20: dep year 2 | E20: =-$D$14/10 -> -3000000 | F20: =-$D$14/10 -> -3000000 | G20: =-$D$14/10 -> -3000000 | H20: =-$D$14/10 -> -3000000 | I20: =-$D$14/10 -> -3000000 | J20: =-$D$14/10 -> -3000000 | K20: =-$D$14/10 -> -3000000 | L20: =-$D$14/10 -> -3000000 | M20: =-$D$14/10 -> -3000000
A21: dep year 3 | F21: =-$E$14/10 -> -3000000 | G21: =-$E$14/10 -> -3000000 | H21: =-$E$14/10 -> -3000000 | I21: =-$E$14/10 -> -3000000 | J21: =-$E$14/10 -> -3000000 | K21: =-$E$14/10 -> -3000000 | L21: =-$E$14/10 -> -3000000 | M21: =-$E$14/10 -> -3000000
A22: dep year 4 | G22: =-$F$14/10 -> -900000 | H22: =-$F$14/10 -> -900000 | I22: =-$F$14/10 -> -900000 | J22: =-$F$14/10 -> -900000 | K22: =-$F$14/10 -> -900000 | L22: =-$F$14/10 -> -900000 | M22: =-$F$14/10 -> -900000
A23: dep year 5 | H23: =-$F$14/10 -> -900000 | I23: =-$F$14/10 -> -900000 | J23: =-$F$14/10 -> -900000 | K23: =-$F$14/10 -> -900000 | L23: =-$F$14/10 -> -900000 | M23: =-$F$14/10 -> -900000
A24: dep year 6 | I24: =-$F$14/10 -> -900000 | J24: =-$F$14/10 -> -900000 | K24: =-$F$14/10 -> -900000 | L24: =-$F$14/10 -> -900000 | M24: =-$F$14/10 -> -900000
A25: dep year 7 | J25: =-$F$14/10 -> -900000 | K25: =-$F$14/10 -> -900000 | L25: =-$F$14/10 -> -900000 | M25: =-$F$14/10 -> -900000
A26: dep year 8 | K26: =-$F$14/10 -> -900000 | L26: =-$F$14/10 -> -900000 | M26: =-$F$14/10 -> -900000
A27: dep year 9 | L27: =-$F$14/10 -> -900000 | M27: =-$F$14/10 -> -900000
A28: dep year 10 | M28: =-$F$14/10 -> -900000
A29: total dep | D29: =SUM(D19:D28) -> -24000000 | E29: =SUM(E19:E28) -> -27000000 | F29: =SUM(F19:F28) -> -30000000 | G29: =SUM(G19:G28) -> -30900000 | H29: =SUM(H19:H28) -> -31800000 | I29: =SUM(I19:I28) -> -32700000 | J29: =SUM(J19:J28) -> -33600000 | K29: =SUM(K19:K28) -> -34500000 | ... M29: =SUM(M19:M28) -> -36300000

Sheet Working capital
A1: WORKING CAPITAL
A3: WC india
A4: DIO | B4: =CHOOSE('Model Assumptions'!B3,'Working capital'!B31,'Working capital'!B32,'Working capital'!B33) -> 40
A5: DSO | B5: =CHOOSE('Model Assumptions'!B3,'Working capital'!B26,'Working capital'!B27,'Working capital'!B28) -> 35
A6: DPO | B6: =CHOOSE('Model Assumptions'!B3,'Working capital'!B37,'Working capital'!B38,'Working capital'!B39) -> 35
A7: Net wc cycle | B7: =B4+B5-B6 -> 40
A9: WC vietnam
A10: DIO | B10: ='Model Assumptions'!B23 -> 35
A11: DSO | B11: ='Model Assumptions'!B22 -> 35
A12: DPO | B12: ='Model Assumptions'!B24 -> 25
A13: Net wc cycle | B13: =B10+B11-B12 -> 45
A16: In euro | D16: 1 | E16: 2 | F16: 3 | G16: 4 | H16: 5 | I16: 6 | J16: 7 | K16: 8 | L16: 9 | M16: 10
A18: Extra production value | D18: ='Saving Forecast '!C11*'Saving Forecast '!C27 -> 50000000 | E18: ='Saving Forecast '!D11*'Saving Forecast '!D27 -> 101200000 | F18: ='Saving Forecast '!E11*'Saving Forecast '!E27 -> 2.04464e+08 | G18: ='Saving Forecast '!F11*'Saving Forecast '!F27 -> 3.0922176e+08 | H18: ='Saving Forecast '!G11*'Saving Forecast '!G27 -> 3.8888158e+08 | I18: ='Saving Forecast '!H11*'Saving Forecast '!H27 -> 4.4238008e+08 | J18: ='Saving Forecast '!I11*'Saving Forecast '!I27 -> 4.689389e+08 | K18: ='Saving Forecast '!J11*'Saving Forecast '!J27 -> 4.9413635e+08 | ... M18: ='Saving Forecast '!L11*'Saving Forecast '!L27 -> 4.8751881e+08
A19: delta net trading cycle | D19: =B13-B7 -> 5 | E19: 5 | F19: 5 | G19: 5 | H19: 5 | I19: 5 | J19: 5 | K19: 5 | L19: 5 | M19: 5
A20: working capital | D20: =-D18*D19/360 -> -694444.44 | E20: =-E18*E19/360 -> -1405555.6 | F20: =-F18*F19/360 -> -2839777.8 | G20: =-G18*G19/360 -> -4294746.7 | H20: =-H18*H19/360 -> -5401133.1 | I20: =-I18*I19/360 -> -6144167.8 | J20: =-J18*J19/360 -> -6513040.3 | K20: =-K18*K19/360 -> -6863004.8 | ... M20: =-M18*M19/360 -> -6771094.6
A21: Delta working capital | D21: =D20 -> -694444.44 | E21: =E20-D20 -> -711111.11 | F21: =F20-E20 -> -1434222.2 | G21: =G20-F20 -> -1454968.9 | H21: =H20-G20 -> -1106386.4 | I21: =I20-H20 -> -743034.69 | J21: =J20-I20 -> -368872.53 | K21: =K20-J20 -> -349964.51 | L21: =L20-K20 -> 33801.512 | M21: =M20-L20 -> 58108.693
A25: wc cases india - DSO
A26: best case | B26: 30
A27: base case | B27: 35
A28: worst case | B28: 40
A30: wc cases india- DIO
A31: best case | B31: 35
A32: base case | B32: 40
A33: worst case | B33: 45
A36: wc cases india- DPO
A37: best case | B37: 30
A38: base case | B38: 35
A39: worst case | B39: 40

Sheet Financing 
A1: FINANCING
A3: INITIAL INVESTMENT | B3: ='Fixed Asset Roll-Forward'!D13 -> 240000000
A5: FINANCING FACILITY
A6: Debt Facility (EUR) | B6: 200000000
A7: Interest rate Debt Facility | B7: 0.09
A8: Repay Debt Facility in | B8: 10
A11: in euros | C11: 0 | D11: 1 | E11: 2 | F11: 3 | G11: 4 | H11: 5 | I11: 6 | J11: 7 | K11: 8 | L11: 9 | M11: 10
A12: Beginning debt | C12: =B6 -> 200000000 | D12: =C15 -> 200000000 | E12: =D15 -> 200000000 | F12: =E15 -> 190000000 | G12: =F15 -> 170000000 | H12: =G15 -> 150000000 | I12: =H15 -> 130000000 | J12: =I15 -> 110000000 | K12: =J15 -> 90000000 | ... M12: =L15 -> 50000000
A13: repayement | C13: =-$B$6*C14 -> 0 | D13: =-$B$6*D14 -> 0 | E13: =-$B$6*E14 -> -10000000 | F13: =-$B$6*F14 -> -20000000 | G13: =-$B$6*G14 -> -20000000 | H13: =-$B$6*H14 -> -20000000 | I13: =-$B$6*I14 -> -20000000 | J13: =-$B$6*J14 -> -20000000 | ... M13: =-$B$6*M14 -> -20000000
A14: repayement % | C14: 0 | D14: 0 | E14: 0.05 | F14: 0.1 | G14: 0.1 | H14: 0.1 | I14: 0.1 | J14: 0.1 | K14: 0.1 | L14: 0.1 | M14: 0.1
A15: Ending debt | C15: =SUM(C12:C13) -> 200000000 | D15: =SUM(D12:D13) -> 200000000 | E15: =SUM(E12:E13) -> 190000000 | F15: =SUM(F12:F13) -> 170000000 | G15: =SUM(G12:G13) -> 150000000 | H15: =SUM(H12:H13) -> 130000000 | I15: =SUM(I12:I13) -> 110000000 | J15: =SUM(J12:J13) -> 90000000 | ... M15: =SUM(M12:M13) -> 30000000
A19: interest expenses | C19: =IF(C11=0,0,-C12*$B$7) -> 0 | D19: =IF(D11=0,0,-D12*$B$7) -> -18000000 | E19: =IF(E11=0,0,-E12*$B$7) -> -18000000 | F19: =IF(F11=0,0,-F12*$B$7) -> -17100000 | G19: =IF(G11=0,0,-G12*$B$7) -> -15300000 | H19: =IF(H11=0,0,-H12*$B$7) -> -13500000 | I19: =IF(I11=0,0,-I12*$B$7) -> -11700000 | J19: =IF(J11=0,0,-J12*$B$7) -> -9900000 | ... M19: =IF(M11=0,0,-M12*$B$7) -> -4500000
A21: VOLUME | C21: 0 | D21: ='Saving Forecast '!C11 -> 20000 | E21: ='Saving Forecast '!D11 -> 40000 | F21: ='Saving Forecast '!E11 -> 80000 | G21: ='Saving Forecast '!F11 -> 120000 | H21: ='Saving Forecast '!G11 -> 150000 | I21: ='Saving Forecast '!H11 -> 170000 | J21: ='Saving Forecast '!I11 -> 180000 | K21: ='Saving Forecast '!J11 -> 190000 | ... M21: ='Saving Forecast '!L11 -> 190000
A22: Volume less than 100000 | C22: =IF(C21<100000,"yes","no") -> yes | D22: =IF(D21<100000,"yes","no") -> yes | E22: =IF(E21<100000,"yes","no") -> yes | F22: =IF(F21<100000,"yes","no") -> yes | G22: =IF(G21<100000,"yes","no") -> no | H22: =IF(H21<100000,"yes","no") -> no | I22: =IF(I21<100000,"yes","no") -> no | J22: =IF(J21<100000,"yes","no") -> no | ... M22: =IF(M21<100000,"yes","no") -> no
A24: penalty | C24: =-IF(C11=0,0,IF(C22="yes",1000000,0)) -> 0 | D24: =-IF(D11=0,0,IF(D22="yes",1000000,0)) -> -1000000 | E24: =-IF(E11=0,0,IF(E22="yes",1000000,0)) -> -1000000 | F24: =-IF(F11=0,0,IF(F22="yes",1000000,0)) -> -1000000 | G24: =-IF(G11=0,0,IF(G22="yes",1000000,0)) -> 0 | H24: =-IF(H11=0,0,IF(H22="yes",1000000,0)) -> 0 | I24: =-IF(I11=0,0,IF(I22="yes",1000000,0)) -> 0 | J24: =-IF(J11=0,0,IF(J22="yes",1000000,0)) -> 0 | ... M24: =-IF(M11=0,0,IF(M22="yes",1000000,0)) -> 0
A27: net cash flow | D27: ='Free Cash Flow Projection'!C13 -> -1444444.4 | E27: ='Free Cash Flow Projection'!D13 -> 27688889 | F27: ='Free Cash Flow Projection'!E13 -> 1.1683878e+08 | G27: ='Free Cash Flow Projection'!F13 -> 1.9771135e+08 | H27: ='Free Cash Flow Projection'!G13 -> 2.593798e+08 | I27: ='Free Cash Flow Projection'!H13 -> 3.0144203e+08 | J27: ='Free Cash Flow Projection'!I13 -> 3.233103e+08 | K27: ='Free Cash Flow Projection'!J13 -> 3.438023e+08 | ... M27: ='Free Cash Flow Projection'!L13 -> 3.4239722e+08
A28: EQUITY FINANCING | D28: =D15+D24+D27 -> 1.9755556e+08 | E28: =IF(E27>0,D28,E27-D28) -> 1.9755556e+08 | F28: =IF(F27>0,E28,F27-E28) -> 1.9755556e+08 | G28: =IF(G27>0,F28,G27-F28) -> 1.9755556e+08 | H28: =IF(H27>0,G28,H27-G28) -> 1.9755556e+08 | I28: =IF(I27>0,H28,I27-H28) -> 1.9755556e+08 | J28: =IF(J27>0,I28,J27-I28) -> 1.9755556e+08 | K28: =IF(K27>0,J28,K27-J28) -> 1.9755556e+08 | L28: =IF(L27>0,K28,L27-K28) -> 1.9755556e+08 | M28: =IF(M27>0,L28,M27-L28) -> 1.9755556e+08

Sheet Profit and loss Statement
A1: Profit and loss statement
C2: 1 | D2: 2 | E2: 3 | F2: 4 | G2: 5 | H2: 6 | I2: 7 | J2: 8 | K2: 9 | L2: 10
A3: Savings (EBITDA) | C3: ='Saving Forecast '!C34 -> 50000000 | D3: ='Saving Forecast '!D34 -> 101200000 | E3: ='Saving Forecast '!E34 -> 2.04464e+08 | F3: ='Saving Forecast '!F34 -> 3.0922176e+08 | G3: ='Saving Forecast '!G34 -> 3.8888158e+08 | H3: ='Saving Forecast '!H34 -> 4.4238008e+08 | I3: ='Saving Forecast '!I34 -> 4.689389e+08 | J3: ='Saving Forecast '!J34 -> 4.9413635e+08 | ... L3: ='Saving Forecast '!L34 -> 4.8751881e+08
A4: D&A | C4: ='Fixed Asset Roll-Forward'!D15 -> -24000000 | D4: ='Fixed Asset Roll-Forward'!E15 -> -27000000 | E4: ='Fixed Asset Roll-Forward'!F15 -> -30000000 | F4: ='Fixed Asset Roll-Forward'!G15 -> -30900000 | G4: ='Fixed Asset Roll-Forward'!H15 -> -31800000 | H4: ='Fixed Asset Roll-Forward'!I15 -> -32700000 | I4: ='Fixed Asset Roll-Forward'!J15 -> -33600000 | J4: ='Fixed Asset Roll-Forward'!K15 -> -34500000 | ... L4: ='Fixed Asset Roll-Forward'!M15 -> -36300000
A5: EBIT | C5: =SUM(C3:C4) -> 26000000 | D5: =SUM(D3:D4) -> 74200000 | E5: =SUM(E3:E4) -> 1.74464e+08 | F5: =SUM(F3:F4) -> 2.7832176e+08 | G5: =SUM(G3:G4) -> 3.5708158e+08 | H5: =SUM(H3:H4) -> 4.0968008e+08 | I5: =SUM(I3:I4) -> 4.353389e+08 | J5: =SUM(J3:J4) -> 4.5963635e+08 | ... L5: =SUM(L3:L4) -> 4.5121881e+08
A6: Interest expenses | C6: ='Financing '!D19 -> -18000000 | D6: ='Financing '!E19 -> -18000000 | E6: ='Financing '!F19 -> -17100000 | F6: ='Financing '!G19 -> -15300000 | G6: ='Financing '!H19 -> -13500000 | H6: ='Financing '!I19 -> -11700000 | I6: ='Financing '!J19 -> -9900000 | J6: ='Financing '!K19 -> -8100000 | ... L6: ='Financing '!M19 -> -4500000
A7: Covenents | C7: ='Financing '!D24 -> -1000000 | D7: ='Financing '!E24 -> -1000000 | E7: ='Financing '!F24 -> -1000000 | F7: ='Financing '!G24 -> 0 | G7: ='Financing '!H24 -> 0 | H7: ='Financing '!I24 -> 0 | I7: ='Financing '!J24 -> 0 | J7: ='Financing '!K24 -> 0 | ... L7: ='Financing '!M24 -> 0
A8: EBT | C8: =SUM(C5:C7) -> 7000000 | D8: =SUM(D5:D7) -> 55200000 | E8: =SUM(E5:E7) -> 1.56364e+08 | F8: =SUM(F5:F7) -> 2.6302176e+08 | G8: =SUM(G5:G7) -> 3.4358158e+08 | H8: =SUM(H5:H7) -> 3.9798008e+08 | I8: =SUM(I5:I7) -> 4.254389e+08 | J8: =SUM(J5:J7) -> 4.5153635e+08 | ... L8: =SUM(L5:L7) -> 4.4671881e+08
A9: Taxes | C9: =IF(-C8*'Model Assumptions'!$B$49>0,0,-C8*'Model Assumptions'!$B$49) -> -1750000 | D9: =IF(-D8*'Model Assumptions'!$B$49>0,0,-D8*'Model Assumptions'!$B$49) -> -13800000 | E9: =IF(-E8*'Model Assumptions'!$B$49>0,0,-E8*'Model Assumptions'!$B$49) -> -39091000 | F9: =IF(-F8*'Model Assumptions'!$B$49>0,0,-F8*'Model Assumptions'!$B$49) -> -65755440 | G9: =IF(-G8*'Model Assumptions'!$B$49>0,0,-G8*'Model Assumptions'!$B$49) -> -85895395 | H9: =IF(-H8*'Model Assumptions'!$B$49>0,0,-H8*'Model Assumptions'!$B$49) -> -99495020 | I9: =IF(-I8*'Model Assumptions'!$B$49>0,0,-I8*'Model Assumptions'!$B$49) -> -1.0635973e+08 | J9: =IF(-J8*'Model Assumptions'!$B$49>0,0,-J8*'Model Assumptions'!$B$49) -> -1.1288409e+08 | ... L9: =IF(-L8*'Model Assumptions'!$B$49>0,0,-L8*'Model Assumptions'!$B$49) -> -1.116797e+08
A10: NET INCOME | C10: =SUM(C8:C9) -> 5250000 | D10: =SUM(D8:D9) -> 41400000 | E10: =SUM(E8:E9) -> 1.17273e+08 | F10: =SUM(F8:F9) -> 1.9726632e+08 | G10: =SUM(G8:G9) -> 2.5768619e+08 | H10: =SUM(H8:H9) -> 2.9848506e+08 | I10: =SUM(I8:I9) -> 3.1907918e+08 | J10: =SUM(J8:J9) -> 3.3865226e+08 | ... L10: =SUM(L8:L9) -> 3.3503911e+08

Sheet Free Cash Flow Projection
A1: Free Cash Flow Projection
A3: in euros | B3: 0 | C3: 1 | D3: 2 | E3: 3 | F3: 4 | G3: 5 | H3: 6 | I3: 7 | J3: 8 | K3: 9 | L3: 10 | N3: residual value
A4: Svings (EBITDA) | C4: ='Saving Forecast '!C34 -> 50000000 | D4: ='Saving Forecast '!D34 -> 101200000 | E4: ='Saving Forecast '!E34 -> 2.04464e+08 | F4: ='Saving Forecast '!F34 -> 3.0922176e+08 | G4: ='Saving Forecast '!G34 -> 3.8888158e+08 | H4: ='Saving Forecast '!H34 -> 4.4238008e+08 | I4: ='Saving Forecast '!I34 -> 4.689389e+08 | J4: ='Saving Forecast '!J34 -> 4.9413635e+08 | ... L4: ='Saving Forecast '!L34 -> 4.8751881e+08
A5: Taxes | C5: ='Profit and loss Statement'!C9 -> -1750000 | D5: ='Profit and loss Statement'!D9 -> -13800000 | E5: ='Profit and loss Statement'!E9 -> -39091000 | F5: ='Profit and loss Statement'!F9 -> -65755440 | G5: ='Profit and loss Statement'!G9 -> -85895395 | H5: ='Profit and loss Statement'!H9 -> -99495020 | I5: ='Profit and loss Statement'!I9 -> -1.0635973e+08 | J5: ='Profit and loss Statement'!J9 -> -1.1288409e+08 | ... L5: ='Profit and loss Statement'!L9 -> -1.116797e+08
A6: Delta working capital | C6: ='Working capital'!D21 -> -694444.44 | D6: ='Working capital'!E21 -> -711111.11 | E6: ='Working capital'!F21 -> -1434222.2 | F6: ='Working capital'!G21 -> -1454968.9 | G6: ='Working capital'!H21 -> -1106386.4 | H6: ='Working capital'!I21 -> -743034.69 | I6: ='Working capital'!J21 -> -368872.53 | J6: ='Working capital'!K21 -> -349964.51 | ... L6: ='Working capital'!M21 -> 58108.693
A7: Capex | C7: =-'Fixed Asset Roll-Forward'!D14 -> -30000000 | D7: =-'Fixed Asset Roll-Forward'!E14 -> -30000000 | E7: =-'Fixed Asset Roll-Forward'!F14 -> -9000000 | F7: =-'Fixed Asset Roll-Forward'!G14 -> -9000000 | G7: =-'Fixed Asset Roll-Forward'!H14 -> -9000000 | H7: =-'Fixed Asset Roll-Forward'!I14 -> -9000000 | I7: =-'Fixed Asset Roll-Forward'!J14 -> -9000000 | J7: =-'Fixed Asset Roll-Forward'!K14 -> -9000000 | ... L7: =-'Fixed Asset Roll-Forward'!M14 -> -9000000
A8: Operating cash flow | C8: =SUM(C4:C7) -> 17555556 | D8: =SUM(D4:D7) -> 56688889 | E8: =SUM(E4:E7) -> 1.5493878e+08 | F8: =SUM(F4:F7) -> 2.3301135e+08 | G8: =SUM(G4:G7) -> 2.928798e+08 | H8: =SUM(H4:H7) -> 3.3314203e+08 | I8: =SUM(I4:I7) -> 3.532103e+08 | J8: =SUM(J4:J7) -> 3.719023e+08 | ... L8: =SUM(L4:L7) -> 3.6689722e+08
A9: Debt repayement | C9: ='Financing '!D13 -> 0 | D9: ='Financing '!E13 -> -10000000 | E9: ='Financing '!F13 -> -20000000 | F9: ='Financing '!G13 -> -20000000 | G9: ='Financing '!H13 -> -20000000 | H9: ='Financing '!I13 -> -20000000 | I9: ='Financing '!J13 -> -20000000 | J9: ='Financing '!K13 -> -20000000 | ... L9: ='Financing '!M13 -> -20000000
A10: Interest expenses | C10: ='Financing '!D19 -> -18000000 | D10: ='Financing '!E19 -> -18000000 | E10: ='Financing '!F19 -> -17100000 | F10: ='Financing '!G19 -> -15300000 | G10: ='Financing '!H19 -> -13500000 | H10: ='Financing '!I19 -> -11700000 | I10: ='Financing '!J19 -> -9900000 | J10: ='Financing '!K19 -> -8100000 | ... L10: ='Financing '!M19 -> -4500000
A11: Covenent penalty | C11: ='Financing '!D24 -> -1000000 | D11: ='Financing '!E24 -> -1000000 | E11: ='Financing '!F24 -> -1000000 | F11: ='Financing '!G24 -> 0 | G11: ='Financing '!H24 -> 0 | H11: ='Financing '!I24 -> 0 | I11: ='Financing '!J24 -> 0 | J11: ='Financing '!K24 -> 0 | ... L11: ='Financing '!M24 -> 0
A12: increase in equity
A13: Project cash flow | C13: =SUM(C8:C11) -> -1444444.4 | D13: =SUM(D8:D11) -> 27688889 | E13: =SUM(E8:E11) -> 1.1683878e+08 | F13: =SUM(F8:F11) -> 1.9771135e+08 | G13: =SUM(G8:G11) -> 2.593798e+08 | H13: =SUM(H8:H11) -> 3.0144203e+08 | I13: =SUM(I8:I11) -> 3.233103e+08 | J13: =SUM(J8:J11) -> 3.438023e+08 | ... L13: =SUM(L8:L11) -> 3.4239722e+08 | N13: ='Model Assumptions'!B51-'Financing '!M15 -> 20000000

Sheet WACC
A1: WACC
A3: Cost of debt | B3: 0.09
A4: Risk- free in vietnam | B4: 0.04
A5: Tax rate | B5: 0.25
A6: Market premium in vietnam | B6: 0.06
A8: Company Leverage (D/E) Beta | B8: Leverage | C8: Beta
A9: Company A | B9: 0.75 | C9: 1
A10: Company B | B10: 0.85 | C10: 1.1
A11: Company C | B11: 0.7 | C11: 0.95
A13: in euros | C13: 0 | D13: 1 | E13: 2 | F13: 3 | G13: 4 | H13: 5 | I13: 6 | J13: 7 | K13: 8 | L13: 9 | M13: 10
A14: debt financing | C14: ='Financing '!C15 -> 200000000 | D14: ='Financing '!D15 -> 200000000 | E14: ='Financing '!E15 -> 190000000 | F14: ='Financing '!F15 -> 170000000 | G14: ='Financing '!G15 -> 150000000 | H14: ='Financing '!H15 -> 130000000 | I14: ='Financing '!I15 -> 110000000 | J14: ='Financing '!J15 -> 90000000 | ... M14: ='Financing '!M15 -> 30000000
A15: equity financing | C15: ='Financing '!D28 -> 1.9755556e+08 | D15: ='Financing '!E28 -> 1.9755556e+08 | E15: ='Financing '!F28 -> 1.9755556e+08 | F15: ='Financing '!G28 -> 1.9755556e+08 | G15: ='Financing '!H28 -> 1.9755556e+08 | H15: ='Financing '!I28 -> 1.9755556e+08 | I15: ='Financing '!J28 -> 1.9755556e+08 | J15: ='Financing '!K28 -> 1.9755556e+08 | ... L15: ='Financing '!M28 -> 1.9755556e+08 | M15: 1.9755556e+08
A16: total financing | C16: =SUM(C14:C15) -> 3.9755556e+08 | D16: =SUM(D14:D15) -> 3.9755556e+08 | E16: =SUM(E14:E15) -> 3.8755556e+08 | F16: =SUM(F14:F15) -> 3.6755556e+08 | G16: =SUM(G14:G15) -> 3.4755556e+08 | H16: =SUM(H14:H15) -> 3.2755556e+08 | I16: =SUM(I14:I15) -> 3.0755556e+08 | J16: =SUM(J14:J15) -> 2.8755556e+08 | ... M16: =SUM(M14:M15) -> 2.2755556e+08
A19: debt financing % | C19: =C14/C16 -> 0.50307434 | D19: =D14/D16 -> 0.50307434 | E19: =E14/E16 -> 0.49025229 | F19: =F14/F16 -> 0.46251511 | G19: =G14/G16 -> 0.43158568 | H19: =H14/H16 -> 0.39687924 | I19: =I14/I16 -> 0.35765896 | J19: =J14/J16 -> 0.312983 | ... M19: =M14/M16 -> 0.13183594
A20: equity financing % | C20: =C15/C16 -> 0.49692566 | D20: =D15/D16 -> 0.49692566 | E20: =E15/E16 -> 0.50974771 | F20: =F15/F16 -> 0.53748489 | G20: =G15/G16 -> 0.56841432 | H20: =H15/H16 -> 0.60312076 | I20: =I15/I16 -> 0.64234104 | J20: =J15/J16 -> 0.687017 | ... M20: =M15/M16 -> 0.86816406
A21: total financing % | C21: =SUM(C19:C20) -> 1 | D21: =SUM(D19:D20) -> 1 | E21: =SUM(E19:E20) -> 1 | F21: =SUM(F19:F20) -> 1 | G21: =SUM(G19:G20) -> 1 | H21: =SUM(H19:H20) -> 1 | I21: =SUM(I19:I20) -> 1 | J21: =SUM(J19:J20) -> 1 | ... M21: =SUM(M19:M20) -> 1
A24: Comparable companies:
A25: Average leverage | B25: =AVERAGE(B9:B11) -> 0.76666667
A26: Average beta | B26: =AVERAGE(C9:C11) -> 1.0166667
A29: Project beta:
A30: Debt / Equity | C30: =C19/C20 -> 1.0123735 | D30: =D19/D20 -> 1.0123735 | E30: =E19/E20 -> 0.96175478 | F30: =F19/F20 -> 0.86051744 | G30: =G19/G20 -> 0.75928009 | H30: =H19/H20 -> 0.65804274 | I30: =I19/I20 -> 0.5568054 | J30: =J19/J20 -> 0.45556805 | ... M30: =M19/M20 -> 0.15185602
A31: Beta unlevered | C31: =$B$26/((1+(1-$B$5)*($B$25))) -> 0.64550265 | D31: =$B$26/((1+(1-$B$5)*($B$25))) -> 0.64550265 | E31: =$B$26/((1+(1-$B$5)*($B$25))) -> 0.64550265 | F31: =$B$26/((1+(1-$B$5)*($B$25))) -> 0.64550265 | G31: =$B$26/((1+(1-$B$5)*($B$25))) -> 0.64550265 | H31: =$B$26/((1+(1-$B$5)*($B$25))) -> 0.64550265 | I31: =$B$26/((1+(1-$B$5)*($B$25))) -> 0.64550265 | J31: =$B$26/((1+(1-$B$5)*($B$25))) -> 0.64550265 | ... M31: =$B$26/((1+(1-$B$5)*($B$25))) -> 0.64550265
A32: Project beta: | C32: =$C$31/((1+(1-$B$5)*(C30))) -> 0.36691295 | D32: =$C$31/((1+(1-$B$5)*(D30))) -> 0.36691295 | E32: =$C$31/((1+(1-$B$5)*(E30))) -> 0.37500529 | F32: =$C$31/((1+(1-$B$5)*(F30))) -> 0.39231027 | G32: =$C$31/((1+(1-$B$5)*(G30))) -> 0.41128963 | H32: =$C$31/((1+(1-$B$5)*(H30))) -> 0.43219872 | I32: =$C$31/((1+(1-$B$5)*(I30))) -> 0.45534763 | J32: =$C$31/((1+(1-$B$5)*(J30))) -> 0.48111662 | ... M32: =$C$31/((1+(1-$B$5)*(M30))) -> 0.579502
A34: cost of equity | C34: =$B$4+$B$6*C32 -> 0.062014777 | D34: =$B$4+$B$6*D32 -> 0.062014777 | E34: =$B$4+$B$6*E32 -> 0.062500318 | F34: =$B$4+$B$6*F32 -> 0.063538616 | G34: =$B$4+$B$6*G32 -> 0.064677378 | H34: =$B$4+$B$6*H32 -> 0.065931923 | I34: =$B$4+$B$6*I32 -> 0.067320858 | J34: =$B$4+$B$6*J32 -> 0.068866997 | ... M34: =$B$4+$B$6*M32 -> 0.07477012
A38: wacc | C38: =C19*(1-$B$5)*$B$3+C20*C34 -> 0.064774252 | D38: =D19*(1-$B$5)*$B$3+D20*D34 -> 0.064774252 | E38: =E19*(1-$B$5)*$B$3+E20*E34 -> 0.064951423 | F38: =F19*(1-$B$5)*$B$3+F20*F34 -> 0.065370816 | G38: =G19*(1-$B$5)*$B$3+G20*G34 -> 0.065895581 | H38: =H19*(1-$B$5)*$B$3+H20*H34 -> 0.06655426 | I38: =I19*(1-$B$5)*$B$3+I20*I34 -> 0.06738493 | J38: =J19*(1-$B$5)*$B$3+J20*J34 -> 0.06843915 | ... M38: =M19*(1-$B$5)*$B$3+M20*M34 -> 0.073811657

Sheet DCF
A1: Discounted cash flow
A4: selected case | B4: ='Model Assumptions'!B3 -> 2
A6: residual value | B6: ='Free Cash Flow Projection'!N13 -> 20000000
A8: in euros | C8: 0 | D8: 1 | E8: 2 | F8: 3 | G8: 4 | H8: 5 | I8: 6 | J8: 7 | K8: 8 | L8: 9 | M8: 10
A10: net cash flow | C10: =-'Financing '!D28 -> -1.9755556e+08 | D10: ='Free Cash Flow Projection'!C13 -> -1444444.4 | E10: ='Free Cash Flow Projection'!D13 -> 27688889 | F10: ='Free Cash Flow Projection'!E13 -> 1.1683878e+08 | G10: ='Free Cash Flow Projection'!F13 -> 1.9771135e+08 | H10: ='Free Cash Flow Projection'!G13 -> 2.593798e+08 | I10: ='Free Cash Flow Projection'!H13 -> 3.0144203e+08 | J10: ='Free Cash Flow Projection'!I13 -> 3.233103e+08 | K10: ='Free Cash Flow Projection'!J13 -> 3.438023e+08 | ... M10: ='Free Cash Flow Projection'!L13 -> 3.4239722e+08
A11: Net Cash Flow + Residual Value | C11: =C10 -> -1.9755556e+08 | D11: =D10 -> -1444444.4 | E11: =E10 -> 27688889 | F11: =F10 -> 1.1683878e+08 | G11: =G10 -> 1.9771135e+08 | H11: =H10 -> 2.593798e+08 | I11: =I10 -> 3.0144203e+08 | J11: =J10 -> 3.233103e+08 | ... L11: =L10 -> 3.4393578e+08 | M11: =M10+B6 -> 3.6239722e+08
A12: cost of equity | D12: =WACC!C34 -> 0.062014777 | E12: =WACC!D34 -> 0.062014777 | F12: =WACC!E34 -> 0.062500318 | G12: =WACC!F34 -> 0.063538616 | H12: =WACC!G34 -> 0.064677378 | I12: =WACC!H34 -> 0.065931923 | J12: =WACC!I34 -> 0.067320858 | K12: =WACC!J34 -> 0.068866997 | ... M12: =WACC!L34 -> 0.072551275
A13: Discounted Cash Flow | C13: =C10/(1+C12)^C8 -> -1.9755556e+08 | D13: =D10/(1+D12)^D8 -> -1360098.3 | E13: =E10/(1+E12)^E8 -> 24549599 | F13: =F10/(1+F12)^F8 -> 97409160 | G13: =G10/(1+G12)^G8 -> 1.5453204e+08 | H13: =H10/(1+H12)^H8 -> 1.8960336e+08 | I13: =I10/(1+I12)^I8 -> 2.0550717e+08 | J13: =J10/(1+J12)^J8 -> 2.0490595e+08 | ... M13: =M10/(1+M12)^M8 -> 1.6996112e+08
A14: Present Value Residual Value | M14: =B6/(1+M12)^M8 -> 9927716.4
A16: Discounted Cash Flow with Residual Value | C16: =C13+C14 -> -1.9755556e+08 | D16: =D13+D14 -> -1360098.3 | E16: =E13+E14 -> 24549599 | F16: =F13+F14 -> 97409160 | G16: =G13+G14 -> 1.5453204e+08 | H16: =H13+H14 -> 1.8960336e+08 | I16: =I13+I14 -> 2.0550717e+08 | J16: =J13+J14 -> 2.0490595e+08 | ... M16: =M13+M14 -> 1.7988884e+08
A19: Sum of Discounted Cash Flows (NPV) | C19: =SUM(C16:M16) -> 1.2454186e+09
A21: IRR | C21: =IRR(C11:M11) -> 0.49354927
H22: senstivity analysis
I23: =C21 -> 0.49354927
H24: =C26 -> 20000000 | I24: 0.49354927
D25: =C21 -> 0.49354927 | H25: 15000000 | I25: 0.49341694
C26: =B6 -> 20000000 | D26: 0.49354927 | H26: 17500000 | I26: 0.49348312
C27: 30000000 | D27: 0.49381346 | H27: 20000000 | I27: 0.49354927
C28: 35000000 | D28: 0.49394533 | H28: 22500000 | I28: 0.49361537
C29: 40000000 | D29: 0.49407704 | H29: 25000000 | I29: 0.49368144
C30: 50000000 | D30: 0.49434002

Sheet Dashboard
A1: Dashboard
B2: Currency in euros
A3: Initial Investment | B3: ='Financing '!B3 -> 240000000 | G3: Initial Investment | H3: 240000000
A4: Debt facility | B4: ='Financing '!B6 -> 200000000 | G4: NPV | H4: 1.2374058e+09
A5: Project Life | B5: ='Fixed Asset Roll-Forward'!B8 -> 10
A6: Residual Value | B6: =DCF!B6 -> 20000000
A7: Cost Of Equity | B7: =WACC!C34 -> 0.062014777
A8: Scenario Case | B8: Base
A10: INVESTMENT APPRAISAL
A12: NPV | B12: =DCF!C19 -> 1.2454186e+09
A13: IRR | B13: =DCF!C21 -> 0.49354927
A15: Decision
A17: ✔ ACCEPT PROJECT
A19: The project generates a significant positive NPV and an
A20: IRR that exceeds the required Cost of Equity. Therefore,
A21: the investment is expected to create shareholder value
A22: and should be accepted.
